weave/__init__.py
weave/tensor.py
weave/_utils/__init__.py
weave/_utils/core.py
weave/cuda/__init__.py
weave/cuda/tools.py
weave/neuro_dataset/__init__.py
weave/neuro_dataset/main.py
weave/neuro_functions/__init__.py
weave/neuro_functions/functions.py
weave/neuro_storage/__init__.py
weave/neuro_storage/loader.py
weave/neuro_storage/saver.py
weave/nn/__init__.py
weave/nn/modules/__init__.py
weave/nn/modules/activations.py
weave/nn/modules/layer.py
weave/nn/modules/losses.py
weave/nn/modules/model.py
weave/nn/optim/__init__.py
weave/nn/optim/optimizers.py
weave/visualization/__init__.py
weave/visualization/weave_weights.py
neuroweave-0.0.8.dist-info/LICENSE
neuroweave-0.0.8.dist-info/METADATA
neuroweave-0.0.8.dist-info/WHEEL
neuroweave-0.0.8.dist-info/top_level.txt
neuroweave-0.0.8.dist-info/RECORD
