Metadata-Version: 2.1
Name: neuroweave
Version: 0.0.8
Summary: A small machine learning library.
Author: Gabriel Niculescu, Carlos Molera, Stanislav Gatin, Patricia Pérez, Hugo Urbán
Author-email: gabriellichu@gmail.com, info.prostaprog@gmail.com, carlosmoleracanals@gmail.com,pperezferre@gmail.com, hugourmaz@gmail.com
Keywords: Python,Machine Learning
Classifier: Development Status :: 4 - Beta
Classifier: Environment :: GPU :: NVIDIA CUDA :: 12
Classifier: Intended Audience :: Education
Classifier: Intended Audience :: Developers
Classifier: Operating System :: Microsoft :: Windows
Classifier: License :: OSI Approved :: MIT License
Classifier: Programming Language :: Python :: 3.12
Classifier: Topic :: Scientific/Engineering :: Artificial Intelligence
Classifier: Topic :: Scientific/Engineering
Requires-Python: >=3.12.0
License-File: LICENSE
Requires-Dist: h5py >=3.11.0
Requires-Dist: numpy >=1.26.4
Requires-Dist: pandas >=2.2.2
Requires-Dist: fastrlock >=0.8.2
Requires-Dist: python-dateutil >=2.9.0.post0
Requires-Dist: pytz >=2024.1
Requires-Dist: six >=1.16.0
Requires-Dist: tzdata >=2024.1
Requires-Dist: matplotlib >=3.9.0
Provides-Extra: gpu
Requires-Dist: cupy-cuda12x ==13.1.0 ; extra == 'gpu'
